README.md
setup.py
Teitoku.egg-info/PKG-INFO
Teitoku.egg-info/SOURCES.txt
Teitoku.egg-info/dependency_links.txt
Teitoku.egg-info/top_level.txt
teitoku/__init__.py
teitoku.egg-info/PKG-INFO
teitoku.egg-info/SOURCES.txt
teitoku.egg-info/dependency_links.txt
teitoku.egg-info/top_level.txt