Metadata-Version: 2.1
Name: teitoku
Version: 0.0.3
Summary: Write once for all chatbot framework
Home-page: https://github.com/yukinotenshi/teitoku
Author: yukinotenshi
Author-email: gabriel.bentara@gmail.com
License: MIT
Keywords: chatbot line telegram discord
Platform: UNKNOWN
